Workbook
Name tax_rate: 'DCF Model'!$C$36
Name UPDATE: 'Data Sheet'!$E$1

Sheet DCF Model
B1: DCF Model For Asian Paints
B3: Financial Modelling
B5: Company OverView
B7: Asian Paints Limited is India's leading paints and home décor company,
B8: offering decorative paints, industrial coatings, waterproofing solutions,
B9: and home improvement products & services.
B11: • Decorative Paints – India's market leader.
B12: • Industrial Coatings – Automotive & protective coatings.
B13: • Home Décor – Kitchens, bath fittings, lighting, furniture & furnishings.
B14: • Beautiful Homes – Painting and interior decor services.
B15: • Waterproofing & Construction Chemicals – Building protection solutions.
B17: Business Highlights:
... B23: Key assumption and Methodology
B26: Parameter | C26: Value | D26: Rationale
B27: Valuation Date
B28: Projection Period
B29: Revenue Growth % | C29: 0.12 | D29: Based on management guidance
B30: Annual Growth Tapering | C30: 0.02
B32: Terminal Growth Rate | C32: 0.05 | D32: Conservative long-term growth in line with India's nominal GDP growth and mature decorative-paints industry potential
B34: Risk-Free Rate(Rf) | C34: 0.068 | D34: 10-year Indian Government Bond yield (approx. July 2026)
B35: Equity Risk Premium(ERP) | C35: =12%-C34 -> 0.052 | D35: Expected return over risk-free rate for equity investors
B36: Tax Rate | C36: 0.25
B38: Financial Performance (₹ Crores)
B39: INCOME STATEMENT
B40: Particulars | C40: 2021 | D40: =C40+1 -> 2022 | E40: =D40+1 -> 2023 | F40: =E40+1 -> 2024 | G40: =F40+1 -> 2025 | H40: =G40+1 -> 2026
B41: Sales | C41: ='Data Sheet'!F17 -> 21712.79 | D41: ='Data Sheet'!G17 -> 29101.28 | E41: ='Data Sheet'!H17 -> 34488.59 | F41: ='Data Sheet'!I17 -> 35494.73 | G41: ='Data Sheet'!J17 -> 33905.62 | H41: ='Data Sheet'!K17 -> 35583.54
B42: % growth | D42: =D41/C41-1 -> 0.34028285 | E42: =E41/D41-1 -> 0.18512278 | F42: =F41/E41-1 -> 0.029173127 | G42: =G41/F41-1 -> -0.044770308 | H42: =H41/G41-1 -> 0.049487961
B43: Cost of Goods Sold | C43: =SUM('Data Sheet'!F18-'Data Sheet'!F19,'Data Sheet'!F20:F21) -> 12487.46 | D43: =SUM('Data Sheet'!G18-'Data Sheet'!G19,'Data Sheet'!G20:G21) -> 18795.96 | E43: =SUM('Data Sheet'!H18-'Data Sheet'!H19,'Data Sheet'!H20:H21) -> 21730.29 | F43: =SUM('Data Sheet'!I18-'Data Sheet'!I19,'Data Sheet'!I20:I21) -> 20675.07 | G43: =SUM('Data Sheet'!J18-'Data Sheet'!J19,'Data Sheet'!J20:J21) -> 20135.49 | H43: =SUM('Data Sheet'!K18-'Data Sheet'!K19,'Data Sheet'!K20:K21) -> 20679.9
B44: % of revenue | C44: =C43/C41 -> 0.57512001 | D44: =D43/D41 -> 0.64588087 | E44: =E43/E41 -> 0.63007186 | F44: =F43/F41 -> 0.58248281 | G44: =G43/G41 -> 0.5938688 | H44: =H43/H41 -> 0.58116477
B45: Gross Profit | C45: =C41-C43 -> 9225.33 | D45: =D41-D43 -> 10305.32 | E45: =E41-E43 -> 12758.3 | F45: =F41-F43 -> 14819.66 | G45: =G41-G43 -> 13770.13 | H45: =H41-H43 -> 14903.64
B46: % Margin | C46: =C45/C41 -> 0.42487999 | D46: =D45/D41 -> 0.35411913 | E46: =E45/E41 -> 0.36992814 | F46: =F45/F41 -> 0.41751719 | G46: =G45/G41 -> 0.4061312 | H46: =H45/H41 -> 0.41883523
B47: Operating Expenses | C47: =SUM('Data Sheet'!F22:F24) -> 4369.73 | D47: =SUM('Data Sheet'!G22:G24) -> 5501.71 | E47: =SUM('Data Sheet'!H22:H24) -> 6498.46 | F47: =SUM('Data Sheet'!I22:I24) -> 7234.68 | G47: =SUM('Data Sheet'!J22:J24) -> 7763.92 | H47: =SUM('Data Sheet'!K22:K24) -> 8203.91
B48: % of revenue | C48: =C47/C41 -> 0.20125143 | D48: =D47/D41 -> 0.18905388 | E48: =E47/E41 -> 0.18842348 | F48: =F47/F41 -> 0.20382406 | G48: =G47/G41 -> 0.22898623 | H48: =H47/H41 -> 0.23055351
B49: EBITDA | C49: =C45-C47 -> 4855.6 | D49: =D45-D47 -> 4803.61 | E49: =E45-E47 -> 6259.84 | F49: =F45-F47 -> 7584.98 | G49: =G45-G47 -> 6006.21 | H49: =H45-H47 -> 6699.73
B50: % Margin | C50: =C49/C41 -> 0.22362856 | D50: =D49/D41 -> 0.16506525 | E50: =E49/E41 -> 0.18150467 | F50: =F49/F41 -> 0.21369313 | G50: =G49/G41 -> 0.17714497 | H50: =H49/H41 -> 0.18828172
B51: Depreciation | C51: ='Data Sheet'!F26 -> 791.27 | D51: ='Data Sheet'!G26 -> 816.36 | E51: ='Data Sheet'!H26 -> 858.02 | F51: ='Data Sheet'!I26 -> 853 | G51: ='Data Sheet'!J26 -> 1026.34 | H51: ='Data Sheet'!K26 -> 1228.85
B52: % of Sales | C52: =C51/C41 -> 0.036442576 | D52: =D51/D41 -> 0.028052374 | E52: =E51/E41 -> 0.024878373 | F52: =F51/F41 -> 0.024031737 | G52: =G51/G41 -> 0.030270498 | H52: =H51/H41 -> 0.034534226
B53: EBIT | C53: =C49-C51 -> 4064.33 | D53: =D49-D51 -> 3987.25 | E53: =E49-E51 -> 5401.82 | F53: =F49-F51 -> 6731.98 | G53: =G49-G51 -> 4979.87 | H53: =H49-H51 -> 5470.88
B54: % Margin | C54: =C53/C41 -> 0.18718599 | D54: =D53/D41 -> 0.13701287 | E54: =E53/E41 -> 0.15662629 | F54: =F53/F41 -> 0.18966139 | G54: =G53/G41 -> 0.14687447 | H54: =H53/H41 -> 0.15374749
B55: Other Income | C55: ='Data Sheet'!F25 -> 331.65 | D55: ='Data Sheet'!G25 -> 295.88 | E55: ='Data Sheet'!H25 -> 431.46 | F55: ='Data Sheet'!I25 -> 820.96 | G55: ='Data Sheet'!J25 -> 350.22 | H55: ='Data Sheet'!K25 -> 727.97
B56: Interest | C56: ='Data Sheet'!F27 -> 91.63 | D56: ='Data Sheet'!G27 -> 95.41 | E56: ='Data Sheet'!H27 -> 144.45 | F56: ='Data Sheet'!I27 -> 205.17 | G56: ='Data Sheet'!J27 -> 227.02 | H56: ='Data Sheet'!K27 -> 195.41
B57: % of debt | C57: =C56/'Data Sheet'!F59 -> 0.083824283 | D57: =D56/'Data Sheet'!G59 -> 0.060124269 | E57: =E56/'Data Sheet'!H59 -> 0.074743095 | F57: =F56/'Data Sheet'!I59 -> 0.082917741 | G57: =G56/'Data Sheet'!J59 -> 0.099122819 | H57: =H56/'Data Sheet'!K59 -> 0.049736188
B58: Profit before tax | C58: =C53+C55-C56 -> 4304.35 | D58: =D53+D55-D56 -> 4187.72 | E58: =E53+E55-E56 -> 5688.83 | F58: =F53+F55-F56 -> 7347.77 | G58: =G53+G55-G56 -> 5103.07 | H58: =H53+H55-H56 -> 6003.44
B59: % of revenue | C59: =C58/C41 -> 0.1982403 | D59: =D58/D41 -> 0.14390157 | E59: =E58/E41 -> 0.16494818 | F59: =F58/F41 -> 0.20701017 | G59: =G58/G41 -> 0.15050809 | H59: =H58/H41 -> 0.16871396
B60: Tax | C60: ='Data Sheet'!F48 -> 389.73 | D60: ='Data Sheet'!G48 -> 321.42 | E60: ='Data Sheet'!H48 -> 391.66 | F60: ='Data Sheet'!I48 -> 373.29 | G60: ='Data Sheet'!J48 -> 415.17 | H60: ='Data Sheet'!K48 -> 428.63
B61: % of PBT | C61: =C60/C58 -> 0.090543288 | D61: =D60/D58 -> 0.076752983 | E61: =E60/E58 -> 0.068847197 | F61: =F60/F58 -> 0.050803169 | G61: =G60/G58 -> 0.081356909 | H61: =H60/H58 -> 0.071397399
B62: Net profit | C62: =C58-C60 -> 3914.62 | D62: =D58-D60 -> 3866.3 | E62: =E58-E60 -> 5297.17 | F62: =F58-F60 -> 6974.48 | G62: =G58-G60 -> 4687.9 | H62: =H58-H60 -> 5574.81
B63: % of revenue | C63: =C62/C41 -> 0.18029097 | D63: =D62/D41 -> 0.1328567 | E63: =E62/E41 -> 0.15359196 | F63: =F62/F41 -> 0.19649339 | G63: =G62/G41 -> 0.13826321 | H63: =H62/H41 -> 0.15666822
B65: BALANCE SHEET
B66: Particulars | C66: 2021 | D66: =C66+1 -> 2022 | E66: =D66+1 -> 2023 | F66: =E66+1 -> 2024 | G66: =F66+1 -> 2025 | H66: =G66+1 -> 2026
B67: Equity Share Capital | C67: ='Data Sheet'!F57 -> 95.92 | D67: ='Data Sheet'!G57 -> 95.92 | E67: ='Data Sheet'!H57 -> 95.92 | F67: ='Data Sheet'!I57 -> 95.92 | G67: ='Data Sheet'!J57 -> 95.92 | H67: ='Data Sheet'!K57 -> 95.92
B68: Reserve | C68: ='Data Sheet'!F58 -> 12710.37 | D68: ='Data Sheet'!G58 -> 13715.64 | E68: ='Data Sheet'!H58 -> 15896.31 | F68: ='Data Sheet'!I58 -> 18632.38 | G68: ='Data Sheet'!J58 -> 19303.89 | H68: ='Data Sheet'!K58 -> 21275.67
B69: Borrowings | C69: ='Data Sheet'!F59 -> 1093.12 | D69: ='Data Sheet'!G59 -> 1586.88 | E69: ='Data Sheet'!H59 -> 1932.62 | F69: ='Data Sheet'!I59 -> 2474.38 | G69: ='Data Sheet'!J59 -> 2290.29 | H69: ='Data Sheet'!K59 -> 3928.93
B70: Other Liabilities | C70: ='Data Sheet'!F60 -> 6455.93 | D70: ='Data Sheet'!G60 -> 7559.99 | E70: ='Data Sheet'!H60 -> 7854.48 | F70: ='Data Sheet'!I60 -> 8698.09 | G70: ='Data Sheet'!J60 -> 8665.15 | H70: ='Data Sheet'!K60 -> 9218.23
B71: Total | C71: =SUM(C67:C70) -> 20355.34 | D71: =SUM(D67:D70) -> 22958.43 | E71: =SUM(E67:E70) -> 25779.33 | F71: =SUM(F67:F70) -> 29900.77 | G71: =SUM(G67:G70) -> 30355.25 | H71: =SUM(H67:H70) -> 34518.75
B72: Net Block | C72: ='Data Sheet'!F62 -> 5858.52 | D72: ='Data Sheet'!G62 -> 5519.06 | E72: ='Data Sheet'!H62 -> 5770.46 | F72: ='Data Sheet'!I62 -> 7146.62 | G72: ='Data Sheet'!J62 -> 9220.1 | H72: ='Data Sheet'!K62 -> 9640.28
B73: Capital Work in Progress | C73: ='Data Sheet'!F63 -> 182.98 | D73: ='Data Sheet'!G63 -> 426.43 | E73: ='Data Sheet'!H63 -> 1019.59 | F73: ='Data Sheet'!I63 -> 2698.37 | G73: ='Data Sheet'!J63 -> 1254.49 | H73: ='Data Sheet'!K63 -> 1848.67
B74: Investments | C74: ='Data Sheet'!F64 -> 4736.8 | D74: ='Data Sheet'!G64 -> 3247.53 | E74: ='Data Sheet'!H64 -> 4261.71 | F74: ='Data Sheet'!I64 -> 4587.92 | G74: ='Data Sheet'!J64 -> 4724.75 | H74: ='Data Sheet'!K64 -> 7061.74
B75: Receivables | C75: ='Data Sheet'!F67 -> 2602.17 | D75: ='Data Sheet'!G67 -> 3871.44 | E75: ='Data Sheet'!H67 -> 4636.94 | F75: ='Data Sheet'!I67 -> 4889.05 | G75: ='Data Sheet'!J67 -> 4313.65 | H75: ='Data Sheet'!K67 -> 4461.8
B76: Inventory | C76: ='Data Sheet'!F68 -> 3798.6 | D76: ='Data Sheet'!G68 -> 6152.98 | E76: ='Data Sheet'!H68 -> 6210.64 | F76: ='Data Sheet'!I68 -> 5923.41 | G76: ='Data Sheet'!J68 -> 6719.27 | H76: ='Data Sheet'!K68 -> 5743.69
B77: Cash & Bank | C77: ='Data Sheet'!F69 -> 610.75 | D77: ='Data Sheet'!G69 -> 864.33 | E77: ='Data Sheet'!H69 -> 843.82 | F77: ='Data Sheet'!I69 -> 1084.01 | G77: ='Data Sheet'!J69 -> 781.98 | H77: ='Data Sheet'!K69 -> 1073.68
B78: Other Assets | C78: =SUM('Data Sheet'!F65-SUM('Data Sheet'!F67:F69)) -> 2565.52 | D78: =SUM('Data Sheet'!G65-SUM('Data Sheet'!G67:G69)) -> 2876.66 | E78: =SUM('Data Sheet'!H65-SUM('Data Sheet'!H67:H69)) -> 3036.17 | F78: =SUM('Data Sheet'!I65-SUM('Data Sheet'!I67:I69)) -> 3571.39 | G78: =SUM('Data Sheet'!J65-SUM('Data Sheet'!J67:J69)) -> 3341.01 | H78: =SUM('Data Sheet'!K65-SUM('Data Sheet'!K67:K69)) -> 4688.89
B79: Total | C79: =SUM(C72:C78) -> 20355.34 | D79: =SUM(D72:D78) -> 22958.43 | E79: =SUM(E72:E78) -> 25779.33 | F79: =SUM(F72:F78) -> 29900.77 | G79: =SUM(G72:G78) -> 30355.25 | H79: =SUM(H72:H78) -> 34518.75
B81: Revenue Projections & Growth Assumptions
B82: Year | C82: FY27E | D82: FY28E | E82: FY29E | F82: FY30E | G82: FY31E | H82: FY32E
B83: Revenue Growth % | C83: =CHOOSE($E$85,C86:H86,C87:H87,C88:H88) -> 0.17 | D83: =CHOOSE($E$85,D86:I86,D87:I87,D88:I88) -> 0.15 | E83: =CHOOSE($E$85,E86:J86,E87:J87,E88:J88) -> 0.13 | F83: =CHOOSE($E$85,F86:K86,F87:K87,F88:K88) -> 0.11 | G83: =CHOOSE($E$85,G86:L86,G87:L87,G88:L88) -> 0.09 | H83: =CHOOSE($E$85,H86:M86,H87:M87,H88:M88) -> 0.07
B84: Revenue (in Crs) | C84: =H41*(1+C83) -> 41632.742 | D84: =C84*(1+D83) -> 47877.653 | E84: =D84*(1+E83) -> 54101.748 | F84: =E84*(1+F83) -> 60052.94 | G84: =F84*(1+G83) -> 65457.705 | H84: =G84*(1+H83) -> 70039.744
B85: Chosen Scenerio | C85: Best case | E85: =MATCH(C85,B86:B88,0) -> 2
B86: Base case | C86: =C29 -> 0.12 | D86: =C86-$C$30 -> 0.1 | E86: =D86-$C$30 -> 0.08 | F86: =E86-$C$30 -> 0.06 | G86: =F86-$C$30 -> 0.04 | H86: =G86-$C$30 -> 0.02
B87: Best case | C87: =C86+5% -> 0.17 | D87: =D86+5% -> 0.15 | E87: =E86+5% -> 0.13 | F87: =F86+5% -> 0.11 | G87: =G86+5% -> 0.09 | H87: =H86+5% -> 0.07
B88: Worst Case | C88: =C86-5% -> 0.07 | D88: =D86-5% -> 0.05 | E88: =E86-5% -> 0.03 | F88: =F86-5% -> 0.01 | G88: =G86-5% -> -0.01 | H88: =H86-5% -> -0.03
B90: Free Cash Flow Projections (₹ Crores)
B91: Particulars | C91: FY27E | D91: FY28E | E91: FY29E | F91: FY30E | G91: FY31E | H91: FY32E
B92: Revenue | C92: =C84 -> 41632.742 | D92: =D84 -> 47877.653 | E92: =E84 -> 54101.748 | F92: =F84 -> 60052.94 | G92: =G84 -> 65457.705 | H92: =H84 -> 70039.744
B93: EBITDA Margin % | C93: =H50 -> 0.18828172 | D93: =C93 -> 0.18828172 | E93: =D93 -> 0.18828172 | F93: =E93 -> 0.18828172 | G93: =F93 -> 0.18828172 | H93: =G93 -> 0.18828172
B94: EBITDA | C94: =C92*C93 -> 7838.6841 | D94: =D92*D93 -> 9014.4867 | E94: =E92*E93 -> 10186.37 | F94: =F92*F93 -> 11306.871 | G94: =G92*G93 -> 12324.489 | H94: =H92*H93 -> 13187.203
B95: Less: Depreciation | C95: =C92*AVERAGE(C52:H52) -> 1236.5603 | D95: =D92*AVERAGE(D52:I52) -> 1357.4962 | E95: =E92*AVERAGE(E52:J52) -> 1538.0428 | F95: =F92*AVERAGE(F52:K52) -> 1778.2969 | G95: =G92*AVERAGE(G52:L52) -> 2120.9842 | H95: =H92*AVERAGE(H52:M52) -> 2418.7683
B96: EBIT | C96: =C94-C95 -> 6602.1238 | D96: =D94-D95 -> 7656.9905 | E96: =E94-E95 -> 8648.3272 | F96: =F94-F95 -> 9528.5738 | G96: =G94-G95 -> 10203.505 | H96: =H94-H95 -> 10768.435
B97: Less: Tax | C97: =C96*tax_rate -> 1650.5309 | D97: =D96*tax_rate -> 1914.2476 | E97: =E96*tax_rate -> 2162.0818 | F97: =F96*tax_rate -> 2382.1435 | G97: =G96*tax_rate -> 2550.8762 | H97: =H96*tax_rate -> 2692.1087
B98: NOPAT | C98: =C96-C97 -> 4951.5928 | D98: =D96-D97 -> 5742.7429 | E98: =E96-E97 -> 6486.2454 | F98: =F96-F97 -> 7146.4304 | G98: =G96-G97 -> 7652.6286 | H98: =H96-H97 -> 8076.3262
B99: Add : Depreciation | C99: =C95 -> 1236.5603 | D99: =D95 -> 1357.4962 | E99: =E95 -> 1538.0428 | F99: =F95 -> 1778.2969 | G99: =G95 -> 2120.9842 | H99: =H95 -> 2418.7683
B100: Less : Reinvestment | C100: =-C98*50% -> -2475.7964 | D100: =-D98*50% -> -2871.3714 | E100: =-E98*50% -> -3243.1227 | F100: =-F98*50% -> -3573.2152 | G100: =-G98*50% -> -3826.3143 | H100: =-H98*50% -> -4038.1631
B101: Free Cash Flow to Firm | C101: =SUM(C98:C100) -> 3712.3567 | D101: =SUM(D98:D100) -> 4228.8677 | E101: =SUM(E98:E100) -> 4781.1655 | F101: =SUM(F98:F100) -> 5351.5121 | G101: =SUM(G98:G100) -> 5947.2985 | H101: =SUM(H98:H100) -> 6456.9314
B103: WACC Calculation
B105: Target Capital Structure
B106: Proportion of Debt | C106: =Comps!F25 -> 0.0025704233
B107: Proportion of Equity | C107: =1-C106 -> 0.99742958
B108: Current Capital Structure
B109: Market Cap | C109: =Comps!E10 -> 256105.81
B110: Total Debt | C110: =Comps!J10 -> 3928.93
B111: Debt/Equity | C111: =C110/C109 -> 0.015341042
B112: Cost of Debt
B113: Pre - Tax Cost of Debt | C113: 0.075
B114: Tax Rate | C114: =tax_rate -> 0.25
B115: After - Tax Cost of Debt | C115: =C113*(1-C114) -> 0.05625
B116: Cost of Equity
B117: Risk Free Rate | C117: =C34 -> 0.068
B118: Equity Risk Premium | C118: =C35 -> 0.052
B119: Levered Equity Beta | C119: =Comps!I25*(1+C111*(1-tax_rate)) -> 0.71289726
B120: Cost of Equity | C120: =C117+C119*C118 -> 0.10507066
...

Sheet Comps
B1: COMPARABLE COMPANY ANALYSIS
B3: Financial Modelling
B7: COMPS Data
B9: Company | C9: Ticker | D9: Price | E9: Market Cap | F9: Sales | G9: EBITDA | H9: Net Income | I9: Beta | J9: Total Debt | K9: Cash & Cash Equivalents | L9: EV/EBITDA | M9: P/E
B10: Asian Paints | C10: ASIANPAINT | D10: ='Data Sheet'!B8 -> 2670 | E10: ='Data Sheet'!B9 -> 256105.81 | F10: ='DCF Model'!H41 -> 35583.54 | G10: ='DCF Model'!H49 -> 6699.73 | H10: ='DCF Model'!H62 -> 5574.81 | I10: 0.87 | J10: ='DCF Model'!H69 -> 3928.93 | K10: ='DCF Model'!H77 -> 1073.68 | L10: =(E10+J10-K10)/G10 -> 38.652462 | M10: =E10/H10 -> 45.939828
B11: Berger Paints | C11: BERGEPAINT | D11: 500 | E11: 59046 | F11: 11880 | G11: 1950 | H11: 1128 | I11: 0.75 | J11: 100 | K11: 364 | L11: =(E11+J11-K11)/G11 -> 30.144615 | M11: =E11/H11 -> 52.345745
B12: Kansai Nerolac | C12: KANSAINER | D12: 201 | E12: 16271 | F12: 8052 | G12: 1100 | H12: 576 | I12: 0.75 | J12: 276 | K12: 1994 | L12: =(E12+J12-K12)/G12 -> 13.23 | M12: =E12/H12 -> 28.248264
B13: Indigo Paints | C13: INDIGOPNTS | D13: 1067 | E13: 5007 | F13: 1330 | G13: 252 | H13: 145 | I13: 0.67 | J13: 10 | K13: 78 | L13: =(E13+J13-K13)/G13 -> 19.599206 | M13: =E13/H13 -> 34.531034
B14: Akzo Nobel India | C14: AKZOINDIA | D14: 3477 | E14: 15835 | F14: 4091 | G14: 530 | H14: 429 | I14: 0.44 | J14: 50 | K14: 550 | L14: =(E14+J14-K14)/G14 -> 28.933962 | M14: =E14/H14 -> 36.911422
B17: Industry Beta
B19: Company Name | C19: Equity Value | D19: Total Debt | E19: Debt/Equity | F19: Debt/Capital | G19: Tax Rate % | H19: Levered Beta | I19: Unlevered Beta
B20: =B11 -> Berger Paints | C20: =E11 -> 59046 | D20: =J11 -> 100 | E20: =D20/C20 -> 0.0016935948 | F20: =D20/(C20+D20) -> 0.0016907314 | G20: =tax_rate -> 0.25 | H20: =I11 -> 0.75 | I20: =H20/(1+E20*(1-tax_rate)) -> 0.74904856
B21: =B12 -> Kansai Nerolac | C21: =E12 -> 16271 | D21: =J12 -> 276 | E21: =D21/C21 -> 0.016962694 | F21: =D21/(C21+D21) -> 0.016679761 | G21: =tax_rate -> 0.25 | H21: =I12 -> 0.75 | I21: =H21/(1+E21*(1-tax_rate)) -> 0.74057835
B22: =B13 -> Indigo Paints | C22: =E13 -> 5007 | D22: =J13 -> 10 | E22: =D22/C22 -> 0.0019972039 | F22: =D22/(C22+D22) -> 0.001993223 | G22: =tax_rate -> 0.25 | H22: =I13 -> 0.67 | I22: =H22/(1+E22*(1-tax_rate)) -> 0.66899791
B23: =B14 -> Akzo Nobel India | C23: =E14 -> 15835 | D23: =J14 -> 50 | E23: =D23/C23 -> 0.0031575624 | F23: =D23/(C23+D23) -> 0.0031476235 | G23: =tax_rate -> 0.25 | H23: =I14 -> 0.44 | I23: =H23/(1+E23*(1-tax_rate)) -> 0.43896047
B24: Average | E24: =AVERAGE(E20:E23) -> 0.0059527639 | F24: =AVERAGE(F20:F23) -> 0.0058778347 | G24: =AVERAGE(G20:G23) -> 0.25 | H24: =AVERAGE(H20:H23) -> 0.6525 | I24: =AVERAGE(I20:I23) -> 0.64939632
B25: Median | E25: =MEDIAN(E20:E23) -> 0.0025773831 | F25: =MEDIAN(F20:F23) -> 0.0025704233 | G25: =MEDIAN(G20:G23) -> 0.25 | H25: =MEDIAN(H20:H23) -> 0.71 | I25: =MEDIAN(I20:I23) -> 0.70478813
B27: Comparable Companies Analysis
B29: Market Data | L29: Financial Data | O29: Valuation
B30: Company Name | C30: Ticker | D30: Price (₹/Share) | E30: Shares Outstanding (Cr) | F30: Market Cap (₹ Cr) | G30: Debt (₹ Cr) | H30: Cash & Cash Equivalents (₹ Cr) | I30: EV (₹ Cr) | J30: Sales (₹ Cr) | K30: EBITDA (₹ Cr) | L30: Net Income (₹ Cr) | M30: EV/Sales (x) | N30: EV/EBITDA (x) | O30: P/E (x)
B31: =B10 -> Asian Paints | C31: =C10 -> ASIANPAINT | D31: =D10 -> 2670 | E31: =F31/D31 -> 95.919779 | F31: =E10 -> 256105.81 | G31: =J10 -> 3928.93 | H31: =K10 -> 1073.68 | I31: =F31+G31-H31 -> 258961.06 | J31: =F10 -> 35583.54 | K31: =G10 -> 6699.73 | L31: =H10 -> 5574.81 | M31: =I31/J31 -> 7.2775519 | N31: =I31/K31 -> 38.652462 | O31: =F31/L31 -> 45.939828
B32: =B11 -> Berger Paints | C32: =C11 -> BERGEPAINT | D32: =D11 -> 500 | E32: =F32/D32 -> 118.092 | F32: =E11 -> 59046 | G32: =J11 -> 100 | H32: =K11 -> 364 | I32: =F32+G32-H32 -> 58782 | J32: =F11 -> 11880 | K32: =G11 -> 1950 | L32: =H11 -> 1128 | M32: =I32/J32 -> 4.9479798 | N32: =I32/K32 -> 30.144615 | O32: =F32/L32 -> 52.345745
B33: =B12 -> Kansai Nerolac | C33: =C12 -> KANSAINER | D33: =D12 -> 201 | E33: =F33/D33 -> 80.950249 | F33: =E12 -> 16271 | G33: =J12 -> 276 | H33: =K12 -> 1994 | I33: =F33+G33-H33 -> 14553 | J33: =F12 -> 8052 | K33: =G12 -> 1100 | L33: =H12 -> 576 | M33: =I33/J33 -> 1.807377 | N33: =I33/K33 -> 13.23 | O33: =F33/L33 -> 28.248264
B34: =B13 -> Indigo Paints | C34: =C13 -> INDIGOPNTS | D34: =D13 -> 1067 | E34: =F34/D34 -> 4.6925961 | F34: =E13 -> 5007 | G34: =J13 -> 10 | H34: =K13 -> 78 | I34: =F34+G34-H34 -> 4939 | J34: =F13 -> 1330 | K34: =G13 -> 252 | L34: =H13 -> 145 | M34: =I34/J34 -> 3.7135338 | N34: =I34/K34 -> 19.599206 | O34: =F34/L34 -> 34.531034
B35: =B14 -> Akzo Nobel India | C35: =C14 -> AKZOINDIA | D35: =D14 -> 3477 | E35: =F35/D35 -> 4.5542134 | F35: =E14 -> 15835 | G35: =J14 -> 50 | H35: =K14 -> 550 | I35: =F35+G35-H35 -> 15335 | J35: =F14 -> 4091 | K35: =G14 -> 530 | L35: =H14 -> 429 | M35: =I35/J35 -> 3.7484723 | N35: =I35/K35 -> 28.933962 | O35: =F35/L35 -> 36.911422
B36: Average | M36: =AVERAGE(M31:M35) -> 4.298983 | N36: =AVERAGE(N31:N35) -> 26.112049 | O36: =AVERAGE(O31:O35) -> 39.595259

Sheet Data Sheet
A1: COMPANY NAME | B1: ASIAN PAINTS LTD | E1: =IF(B2<>B3, "A NEW VERSION OF THE WORKSHEET IS AVAILABLE", "")
A2: LATEST VERSION | B2: 2.1 | E2: PLEASE DO NOT MAKE ANY CHANGES TO THIS SHEET
A3: CURRENT VERSION | B3: 2.1
A5: META
A6: Number of shares | B6: =IF(B9>0, B9/B8, 0) -> 95.919779
A7: Face Value | B7: 1
A8: Current Price | B8: 2670
A9: Market Capitalization | B9: 256105.81
A15: PROFIT & LOSS
A16: Report Date | B16: 42825 | C16: 43190 | D16: 43555 | E16: 43921 | F16: 44286 | G16: 44651 | H16: 45016 | I16: 45382 | J16: 45747 | K16: 46112
A17: Sales | B17: 15061.99 | C17: 16824.55 | D17: 19240.13 | E17: 20211.25 | F17: 21712.79 | G17: 29101.28 | H17: 34488.59 | I17: 35494.73 | J17: 33905.62 | K17: 35583.54
A18: Raw Material Cost | B18: 7452.6 | C18: 8128.17 | D18: 9974.4 | E18: 9981.99 | F18: 10425.55 | G18: 17123.25 | H18: 18985.53 | I18: 17410.84 | J18: 17504.51 | K18: 17142.01
A19: Change in Inventory | B19: 528.6 | C19: -142.13 | D19: 293.26 | E19: 239.15 | F19: 92.45 | G19: 1324.97 | H19: 309.73 | I19: -363.8 | J19: 205 | K19: -603.68
A20: Power and Fuel | B20: 106.02 | C20: 110.3 | D20: 119.63 | E20: 97.79 | F20: 86.05 | G20: 117.23 | H20: 138.29 | I20: 133.25 | J20: 148.58 | K20: 167.1
A21: Other Mfr. Exp | B21: 1662.75 | C21: 1691.68 | D21: 1862.35 | E21: 1946.12 | F21: 2068.31 | G21: 2880.45 | H21: 2916.2 | I21: 2767.18 | J21: 2687.4 | K21: 2767.11
A22: Employee Cost | B22: 1039.89 | C22: 1121.89 | D22: 1242.69 | E22: 1371.27 | F22: 1547.61 | G22: 1794.61 | H22: 2036.41 | I22: 2334.92 | J22: 2605.78 | K22: 2809.73
A23: Selling and admin | B23: 4364.04 | C23: 2254.92 | D23: 2366.87 | E23: 2311.51 | F23: 2245.69 | G23: 2941.98 | H23: 3500.84 | I23: 3811.86 | J23: 3874.94 | K23: 4112.07
A24: Other Expenses | B24: -2028.47 | C24: 171.45 | D24: 202.51 | E24: 579.95 | F24: 576.43 | G24: 765.12 | H24: 961.21 | I24: 1087.9 | J24: 1283.2 | K24: 1282.11
A25: Other Income | B25: 337.9 | C25: 336.41 | D25: 273.77 | E25: 350.1 | F25: 331.65 | G25: 295.88 | H25: 431.46 | I25: 820.96 | J25: 350.22 | K25: 727.97
A26: Depreciation | B26: 334.79 | C26: 360.47 | D26: 622.14 | E26: 780.5 | F26: 791.27 | G26: 816.36 | H26: 858.02 | I26: 853 | J26: 1026.34 | K26: 1228.85
A27: Interest | B27: 37.33 | C27: 41.47 | D27: 110.47 | E27: 102.33 | F27: 91.63 | G27: 95.41 | H27: 144.45 | I27: 205.17 | J27: 227.02 | K27: 195.41
... A31: Dividend Amount | B31: 987.98 | C31: 834.5 | D31: 1007.16 | E31: 1151.04 | F31: 1712.17 | G31: 1836.87 | H31: 2460.35 | I31: 3194.14 | J31: 2378.82 | K31: 2637.8
A40: Quarters
A41: Report Date | B41: 45291 | C41: 45382 | D41: 45473 | E41: 45565 | F41: 45657 | G41: 45747 | H41: 45838 | I41: 45930 | J41: 46022 | K41: 46112
A42: Sales | B42: 9103.09 | C42: 8730.76 | D42: 8969.73 | E42: 8027.54 | F42: 8549.44 | G42: 8358.91 | H42: 8938.55 | I42: 8531.27 | J42: 8867.02 | K42: 9246.7
A43: Expenses | B43: 7047 | C43: 7039.39 | D43: 7275.96 | E43: 6788.03 | F43: 6912.71 | G43: 6922.71 | H43: 7313.58 | I43: 7027.89 | J43: 7086.06 | K43: 7460.09
A44: Other Income | B44: 186.46 | C44: 212.43 | D44: 192.93 | E44: 24.53 | F44: 192.82 | G44: -60.06 | H44: 229.11 | I44: 236.94 | J44: 69.14 | K44: 196.59
A45: Depreciation | B45: 220.35 | C45: 225.61 | D45: 227.7 | E45: 241.99 | F45: 255.55 | G45: 301.1 | H45: 300.87 | I45: 304.93 | J45: 313.07 | K45: 309.98
A46: Interest | B46: 54.42 | C46: 54.1 | D46: 55.38 | E46: 63.01 | F46: 55.84 | G46: 52.79 | H46: 44.5 | I46: 43.87 | J46: 47.94 | K46: 59.1
A47: Profit before tax | B47: 1967.78 | C47: 1624.09 | D47: 1603.62 | E47: 959.04 | F47: 1518.16 | G47: 1022.25 | H47: 1508.71 | I47: 1391.52 | J47: 1489.09 | K47: 1614.12
A48: Tax | B48: 492.62 | C48: 348.79 | D48: 416.83 | E48: 265.38 | F48: 389.73 | G48: 321.42 | H48: 391.66 | I48: 373.29 | J48: 415.17 | K48: 428.63
A49: Net profit | B49: 1447.72 | C49: 1256.72 | D49: 1169.98 | E49: 694.64 | F49: 1110.48 | G49: 692.13 | H49: 1099.77 | I49: 993.59 | J49: 1059.87 | K49: 1172.12
A50: Operating Profit | B50: 2056.09 | C50: 1691.37 | D50: 1693.77 | E50: 1239.51 | F50: 1636.73 | G50: 1436.2 | H50: 1624.97 | I50: 1503.38 | J50: 1780.96 | K50: 1786.61
A55: BALANCE SHEET
A56: Report Date | B56: 42825 | C56: 43190 | D56: 43555 | E56: 43921 | F56: 44286 | G56: 44651 | H56: 45016 | I56: 45382 | J56: 45747 | K56: 46112
A57: Equity Share Capital | B57: 95.92 | C57: 95.92 | D57: 95.92 | E57: 95.92 | F57: 95.92 | G57: 95.92 | H57: 95.92 | I57: 95.92 | J57: 95.92 | K57: 95.92
A58: Reserves | B58: 7507.97 | C58: 8314.31 | D58: 9374.63 | E58: 10034.24 | F58: 12710.37 | G58: 13715.64 | H58: 15896.31 | I58: 18632.38 | J58: 19303.89 | K58: 21275.67
A59: Borrowings | B59: 560.34 | C59: 533.43 | D59: 1319.6 | E59: 1118.5 | F59: 1093.12 | G59: 1586.88 | H59: 1932.62 | I59: 2474.38 | J59: 2290.29 | K59: 3928.93
A60: Other Liabilities | B60: 4240.96 | C60: 4819.82 | D60: 5458.69 | E60: 4889.31 | F60: 6455.93 | G60: 7559.99 | H60: 7854.48 | I60: 8698.09 | J60: 8665.15 | K60: 9218.23
A61: Total | B61: 12405.19 | C61: 13763.48 | D61: 16248.84 | E61: 16137.97 | F61: 20355.34 | G61: 22958.43 | H61: 25779.33 | I61: 29900.77 | J61: 30355.25 | K61: 34518.75
A62: Net Block | B62: 3303.74 | C62: 3732.24 | D62: 6496.56 | E62: 6272.31 | F62: 5858.52 | G62: 5519.06 | H62: 5770.46 | I62: 7146.62 | J62: 9220.1 | K62: 9640.28
A63: Capital Work in Progress | B63: 257.54 | C63: 1405.11 | D63: 209.67 | E63: 140.24 | F63: 182.98 | G63: 426.43 | H63: 1019.59 | I63: 2698.37 | J63: 1254.49 | K63: 1848.67
A64: Investments | B64: 2651.99 | C64: 2140.7 | D64: 2568.58 | E64: 2018.85 | F64: 4736.8 | G64: 3247.53 | H64: 4261.71 | I64: 4587.92 | J64: 4724.75 | K64: 7061.74
A65: Other Assets | B65: 6191.92 | C65: 6485.43 | D65: 6974.03 | E65: 7706.57 | F65: 9577.04 | G65: 13765.41 | H65: 14727.57 | I65: 15467.86 | J65: 15155.91 | K65: 15968.06
A66: Total | B66: 12405.19 | C66: 13763.48 | D66: 16248.84 | E66: 16137.97 | F66: 20355.34 | G66: 22958.43 | H66: 25779.33 | I66: 29900.77 | J66: 30355.25 | K66: 34518.75
A67: Receivables | B67: 1446.6 | C67: 1730.63 | D67: 1907.33 | E67: 1795.22 | F67: 2602.17 | G67: 3871.44 | H67: 4636.94 | I67: 4889.05 | J67: 4313.65 | K67: 4461.8
... A70: No. of Equity Shares | B70: 959197790 | C70: 959197790 | D70: 959197790 | E70: 959197790 | F70: 959197790 | G70: 959197790 | H70: 959197790 | I70: 959197790 | J70: 959197790 | K70: 959197790
A71: New Bonus Shares
A72: Face value | B72: 1 | C72: 1 | D72: 1 | E72: 1 | F72: 1 | G72: 1 | H72: 1 | I72: 1 | J72: 1 | K72: 1
A80: CASH FLOW:
A81: Report Date | B81: 42825 | C81: 43190 | D81: 43555 | E81: 43921 | F81: 44286 | G81: 44651 | H81: 45016 | I81: 45382 | J81: 45747 | K81: 46112
A82: Cash from Operating Activity | B82: 1527.33 | C82: 2113.44 | D82: 2469.54 | E82: 3038.15 | F82: 3683.35 | G82: 986.49 | H82: 4193.43 | I82: 6103.6 | J82: 4423.96 | K82: 7088.18
A83: Cash from Investing Activity | B83: -681.11 | C83: -1556.14 | D83: -917.79 | E83: -517.91 | F83: -540.54 | G83: -316.75 | H83: -1282.34 | I83: -2548.48 | J83: -940.91 | K83: -1328.23
A84: Cash from Financing Activity | B84: -756.43 | C84: -1379.14 | D84: -1117.46 | E84: -2871.46 | F84: -650.4 | G84: -1807.61 | H84: -2140.05 | I84: -2982.5 | J84: -3752.58 | K84: -2376.51
A85: Net Cash Flow | B85: 89.79 | C85: -821.84 | D85: 434.29 | E85: -351.22 | F85: 2492.41 | G85: -1137.87 | H85: 771.04 | I85: 572.62 | J85: -269.53 | K85: 3383.44
F86: =SUM(E67:E68)-SUM(F67:F68) -> -1215.74 | G86: =SUM(F67:F68)-SUM(G67:G68) -> -3623.65 | H86: =SUM(G67:G68)-SUM(H67:H68) -> -823.16 | I86: =SUM(H67:H68)-SUM(I67:I68) -> 35.12 | J86: =SUM(I67:I68)-SUM(J67:J68) -> -220.46 | K86: =SUM(J67:J68)-SUM(K67:K68) -> 827.43
F87: =F86+F83 -> -1756.28 | G87: =G86+G83 -> -3940.4 | H87: =H86+H83 -> -2105.5 | I87: =I86+I83 -> -2513.36 | J87: =J86+J83 -> -1161.37 | K87: =K86+K83 -> -500.8
A88: NOPAT | F88: ='DCF Model'!C53*(1-tax_rate) -> 3048.2475 | G88: ='DCF Model'!D53*(1-tax_rate) -> 2990.4375 | H88: ='DCF Model'!E53*(1-tax_rate) -> 4051.365 | I88: ='DCF Model'!F53*(1-tax_rate) -> 5048.985 | J88: ='DCF Model'!G53*(1-tax_rate) -> 3734.9025 | K88: ='DCF Model'!H53*(1-tax_rate) -> 4103.16
F89: =F87/F88 -> -0.57616056 | G89: =G87/G88 -> -1.3176667 | H89: =H87/H88 -> -0.51970138 | I89: =I87/I88 -> -0.4977951 | J89: =J87/J88 -> -0.31095055 | K89: =K87/K88 -> -0.12205227
A91: PRICE: | B91: 1073.5 | C91: 1120.4 | D91: 1492.7 | E91: 1666.5 | F91: 2537.4 | G91: 3079.95 | H91: 2761.65 | I91: 2846.75 | J91: 2340.65 | K91: 2165.2
A93: DERIVED:
A94: Adjusted Equity Shares in Cr | B94: 95.92 | C94: 95.92 | D94: 95.92 | E94: 95.92 | F94: 95.92 | G94: 95.92 | H94: 95.92 | I94: 95.92 | J94: 95.92 | K94: 95.92
